[
  {
    "id": "REL1757367836244",
    "dadosTurno": {
      "data": "2025-09-08",
      "horario": "07:00 - 19:00",
      "letra": "A",
      "supervisor": "Ozias"
    },
    "equipes": [
      {
        "tipo": "Alta Pressao",
        "numero": "",
        "motorista": "Gerlanio Silves",
        "operadores": "Fabricio Fabiano e Ronald",
        "area": "Sinterizao",
        "atividade": "Limpeza de estruturas",
        "tipoAtividade": "Rotineira",
        "statusAtividade": "Concludo",
        "pendencia": "",
        "observacoes": "",
        "vaga": "ALTA PRESSAO - GPS - 01 - 24 HS",
        "equipamento": "EGC2983",
        "atraso": {
          "houve": "No",
          "horarioDirecionamento": "",
          "motivo": "",
          "justificativa": ""
        },
        "trocas": [],
        "implementos": {
          "implemento_Pistola": "OK",
          "implemento_Pistola_C_L_": "N/A",
          "implemento_Mang__Torpedo": "N/A",
          "implemento_Pedal": "N/A",
          "implemento_Varetas": "N/A",
          "implemento_Rabicho": "N/A",
          "implemento_Lances_Mangueira": "4",
          "implemento_Lances_Varetas": "N/A",
          "justificativa_implementos": "",
          "caixa_bloqueio": "Sim",
          "cadeados": "4",
          "plaquetas": "3"
        }
      },
      {
        "tipo": "Alta Pressao",
        "numero": "",
        "motorista": "Adelson Alves",
        "operadores": "Paulo Cesar e David Silveira Vasconcelos",
        "area": "Escarfagem",
        "atividade": "mesa  virador da maquina 01",
        "tipoAtividade": "Rotineira",
        "statusAtividade": "Concludo",
        "pendencia": "",
        "observacoes": "",
        "vaga": "ALTA PRESSAO - GPS - 08 - 24 HS",
        "equipamento": "EGC2985",
        "atraso": {
          "houve": "No",
          "horarioDirecionamento": "",
          "motivo": "",
          "justificativa": ""
        },
        "trocas": [],
        "implementos": {
          "implemento_Pistola": "OK",
          "implemento_Pistola_C_L_": "N/A",
          "implemento_Mang__Torpedo": "OK",
          "implemento_Pedal": "N/A",
          "implemento_Varetas": "N/A",
          "implemento_Rabicho": "N/A",
          "implemento_Lances_Mangueira": "4",
          "implemento_Lances_Varetas": "N/A",
          "justificativa_implementos": "",
          "caixa_bloqueio": "Sim",
          "cadeados": "5",
          "plaquetas": "5"
        }
      },
      {
        "tipo": "Alta Pressao",
        "numero": "",
        "motorista": "Cristhian",
        "operadores": "Mateus Figueiredo e Josu",
        "area": "Patio de carvao",
        "atividade": "Limpeza de estruturas",
        "tipoAtividade": "Rotineira",
        "statusAtividade": "Concludo",
        "pendencia": "",
        "observacoes": "",
        "vaga": "ALTA PRESSAO - GPS - 07 - 16 HS",
        "equipamento": "EGC2989",
        "atraso": {
          "houve": "No",
          "horarioDirecionamento": "",
          "motivo": "",
          "justificativa": ""
        },
        "trocas": [],
        "implementos": {
          "implemento_Pistola": "OK",
          "implemento_Pistola_C_L_": "N/A",
          "implemento_Mang__Torpedo": "N/A",
          "implemento_Pedal": "OK",
          "implemento_Varetas": "N/A",
          "implemento_Rabicho": "N/A",
          "implemento_Lances_Mangueira": "3",
          "implemento_Lances_Varetas": "N/A",
          "justificativa_implementos": "",
          "caixa_bloqueio": "No",
          "cadeados": "N/A",
          "plaquetas": "N/A"
        }
      },
      {
        "tipo": "Auto Vacuo / Hiper Vacuo",
        "numero": "",
        "motorista": "Ozias oliveira",
        "operadores": "Valdeci",
        "area": "Area interna da usiminas",
        "atividade": "suco de condensado de BFG",
        "tipoAtividade": "Rotineira",
        "statusAtividade": "Concludo",
        "pendencia": "",
        "observacoes": "",
        "vaga": "ALTA PRESSAO - GPS - 02",
        "equipamento": "EAM3257",
        "atraso": {
          "houve": "No",
          "horarioDirecionamento": "",
          "motivo": "",
          "justificativa": ""
        },
        "trocas": [],
        "implementos": {
          "implemento_Mangotes": "OK",
          "implemento_Reducoes": "N/A",
          "implemento_Mangotes_3_": "10 metros",
          "implemento_Mangotes_4_": "N/A",
          "implemento_Mangotes_6_": "N/A",
          "justificativa_implementos": "",
          "caixa_bloqueio": "No",
          "cadeados": "N/A",
          "plaquetas": "N/A"
        }
      },
      {
        "tipo": "Auto Vacuo / Hiper Vacuo",
        "numero": "",
        "motorista": "Walace das Graas",
        "operadores": "Vinicios Valentin",
        "area": "Escarfagem",
        "atividade": "Aguardando",
        "tipoAtividade": "Rotineira",
        "statusAtividade": "Concludo",
        "pendencia": "",
        "observacoes": "",
        "vaga": "AUTO VACUO - GPS - 08 - 24 HS",
        "equipamento": "EGC2983",
        "atraso": {
          "houve": "No",
          "horarioDirecionamento": "",
          "motivo": "",
          "justificativa": ""
        },
        "trocas": [
          {
            "motivo": "Defeitos Em Geral",
            "placaNova": "EAM 3251",
            "defeito": "realizado a troca e passado situao para servitec",
            "dataHoraInicio": "2025-09-08T09:20",
            "dataHoraFim": "2025-09-08T09:26"
          }
        ],
        "implementos": {
          "implemento_Mangotes": "N/A",
          "implemento_Reducoes": "N/A",
          "implemento_Mangotes_3_": "N/A",
          "implemento_Mangotes_4_": "N/A",
          "implemento_Mangotes_6_": "N/A",
          "justificativa_implementos": "",
          "caixa_bloqueio": "No",
          "cadeados": "N/A",
          "plaquetas": "N/A"
        }
      },
      {
        "tipo": "Alta Pressao",
        "numero": "",
        "motorista": "N/A",
        "operadores": "Joao paulo",
        "area": "Coqueria 02",
        "atividade": "Aguardando",
        "tipoAtividade": "Rotineira",
        "statusAtividade": "Concludo",
        "pendencia": "",
        "observacoes": "",
        "vaga": "Moto bomba 01",
        "equipamento": "Moto bomba 01",
        "atraso": {
          "houve": "No",
          "horarioDirecionamento": "",
          "motivo": "",
          "justificativa": ""
        },
        "trocas": [],
        "implementos": {
          "implemento_Pistola": "N/A",
          "implemento_Pistola_C_L_": "N/A",
          "implemento_Mang__Torpedo": "N/A",
          "implemento_Pedal": "N/A",
          "implemento_Varetas": "N/A",
          "implemento_Rabicho": "N/A",
          "implemento_Lances_Mangueira": "11",
          "implemento_Lances_Varetas": "N/A",
          "justificativa_implementos": "",
          "caixa_bloqueio": "No",
          "cadeados": "N/A",
          "plaquetas": "N/A"
        }
      }
    ],
    "observacoesGerais": "",
    "estatisticas": {
      "totalEquipes": 6,
      "equipesAltaPressao": 4,
      "equipesVacuo": 0,
      "equipesExtras": 0,
      "atividadesConcluidas": 6,
      "totalTrocas": 1,
      "equipesComAtraso": 0
    },
    "criadoPor": "GrupoGPS",
    "criadoEm": "2025-09-08T21:43:56.244Z"
  },
  {
    "id": "REL1756975635699",
    "dadosTurno": {
      "data": "2025-09-03",
      "horario": "07:00 - 19:00",
      "letra": "A",
      "supervisor": "Ozias"
    },
    "equipes": [
      {
        "tipo": "Alta Pressao",
        "numero": "",
        "motorista": "Gerlanio Silves",
        "operadores": "Fabricio Fabian e Bruno Matias",
        "area": "Alto forno",
        "atividade": "Limpeza de peneira ,estruturas.",
        "tipoAtividade": "Rotineira",
        "statusAtividade": "Concludo",
        "pendencia": "",
        "observacoes": "",
        "vaga": "ALTA PRESSAO - GPS - 01 - 24 HS",
        "equipamento": "DSY6F81",
        "atraso": {
          "houve": "No",
          "horarioDirecionamento": "",
          "motivo": "",
          "justificativa": ""
        },
        "trocas": [],
        "implementos": {
          "implemento_Pistola": "OK",
          "implemento_Pistola_C_L_": "N/A",
          "implemento_Mang__Torpedo": "N/A",
          "implemento_Pedal": "N/A",
          "implemento_Varetas": "N/A",
          "implemento_Rabicho": "N/A",
          "implemento_Lances_Mangueira": "3",
          "implemento_Lances_Varetas": "N/A",
          "justificativa_implementos": "",
          "caixa_bloqueio": "Sim",
          "cadeados": "4",
          "plaquetas": "3"
        }
      },
      {
        "tipo": "Alta Pressao",
        "numero": "",
        "motorista": "Adelson Alves",
        "operadores": "Paulo Cesar e Ozias Oliveira",
        "area": "Ena e Cral 01",
        "atividade": "Limpeza da bacia do filtro prensa e tubulaes da bomba recalque",
        "tipoAtividade": "Rotineira",
        "statusAtividade": "Concludo",
        "pendencia": "",
        "observacoes": "",
        "vaga": "ALTA PRESSAO - GPS - 08 - 24 HS",
        "equipamento": "EGC2985",
        "atraso": {
          "houve": "No",
          "horarioDirecionamento": "",
          "motivo": "",
          "justificativa": ""
        },
        "trocas": [],
        "implementos": {
          "implemento_Pistola": "OK",
          "implemento_Pistola_C_L_": "N/A",
          "implemento_Mang__Torpedo": "OK",
          "implemento_Pedal": "OK",
          "implemento_Varetas": "N/A",
          "implemento_Rabicho": "N/A",
          "implemento_Lances_Mangueira": "3",
          "implemento_Lances_Varetas": "N/A",
          "justificativa_implementos": "",
          "caixa_bloqueio": "Sim",
          "cadeados": "6",
          "plaquetas": "7"
        }
      },
      {
        "tipo": "Alta Pressao",
        "numero": "",
        "motorista": "N/A",
        "operadores": "Joao Paulo e Jos Eugenio",
        "area": "Coqueria 02",
        "atividade": "Limpeza de portas e pisos",
        "tipoAtividade": "Rotineira",
        "statusAtividade": "Concludo",
        "pendencia": "",
        "observacoes": "Claudinei de Souza no veio trabalhar(atestado) Jose Eugenio fez hora extra no lugar do mesmo",
        "vaga": "Moto bomba 01",
        "equipamento": "Moto bomba 01",
        "atraso": {
          "houve": "No",
          "horarioDirecionamento": "",
          "motivo": "",
          "justificativa": ""
        },
        "trocas": [],
        "implementos": {
          "implemento_Pistola": "OK",
          "implemento_Pistola_C_L_": "N/A",
          "implemento_Mang__Torpedo": "N/A",
          "implemento_Pedal": "N/A",
          "implemento_Varetas": "N/A",
          "implemento_Rabicho": "N/A",
          "implemento_Lances_Mangueira": "11",
          "implemento_Lances_Varetas": "N/A",
          "justificativa_implementos": "",
          "caixa_bloqueio": "No",
          "cadeados": "N/A",
          "plaquetas": "N/A"
        }
      },
      {
        "tipo": "Auto Vacuo / Hiper Vacuo",
        "numero": "",
        "motorista": "Diego Claudio",
        "operadores": "Gilson do Carmo",
        "area": "rea interna da Usiminas",
        "atividade": "Suco de condensado de COG",
        "tipoAtividade": "Rotineira",
        "statusAtividade": "Concludo",
        "pendencia": "",
        "observacoes": "",
        "vaga": "AUTO VACUO - GPS - 01 - 16 HS",
        "equipamento": "ALY5322",
        "atraso": {
          "houve": "No",
          "horarioDirecionamento": "",
          "motivo": "",
          "justificativa": ""
        },
        "trocas": [],
        "implementos": {
          "implemento_Mangotes": "OK",
          "implemento_Reducoes": "N/A",
          "implemento_Mangotes_3_": "10 metros",
          "implemento_Mangotes_4_": "N/A",
          "implemento_Mangotes_6_": "N/A",
          "justificativa_implementos": "",
          "caixa_bloqueio": "No",
          "cadeados": "N/A",
          "plaquetas": "N/A"
        }
      },
      {
        "tipo": "Auto Vacuo / Hiper Vacuo",
        "numero": "",
        "motorista": "Walace das Graas",
        "operadores": "David Silveira Vasconcelos",
        "area": "Ena",
        "atividade": "suco de lama da bacia do filtro prensa e tanque do clarificador",
        "tipoAtividade": "Rotineira",
        "statusAtividade": "Concludo",
        "pendencia": "",
        "observacoes": "",
        "vaga": "AUTO VACUO - GPS - 08 - 24 HS",
        "equipamento": "EGC2993",
        "atraso": {
          "houve": "No",
          "horarioDirecionamento": "",
          "motivo": "",
          "justificativa": ""
        },
        "trocas": [],
        "implementos": {
          "implemento_Mangotes": "OK",
          "implemento_Reducoes": "OK",
          "implemento_Mangotes_3_": "10 metros",
          "implemento_Mangotes_4_": "10 metros",
          "implemento_Mangotes_6_": "N/A",
          "justificativa_implementos": "",
          "caixa_bloqueio": "No",
          "cadeados": "N/A",
          "plaquetas": "N/A"
        }
      }
    ],
    "observacoesGerais": "",
    "estatisticas": {
      "totalEquipes": 5,
      "equipesAltaPressao": 3,
      "equipesVacuo": 0,
      "equipesExtras": 0,
      "atividadesConcluidas": 5,
      "totalTrocas": 0,
      "equipesComAtraso": 0
    },
    "criadoPor": "GrupoGPS",
    "criadoEm": "2025-09-04T08:47:15.699Z"
  },
  {
    "id": "REL1756674840591",
    "dadosTurno": {
      "data": "2025-08-31",
      "horario": "07:00 - 19:00",
      "letra": "A",
      "supervisor": "Ozias"
    },
    "equipes": [
      {
        "tipo": "Alta Pressao",
        "numero": "",
        "motorista": "Gerlanio Silves",
        "operadores": "Fabricio Fabiano e Vinicios Valentim",
        "area": "Sinterizaao",
        "atividade": "Limpeza de estruturas , sistema c",
        "tipoAtividade": "Rotineira",
        "statusAtividade": "Concludo",
        "pendencia": "",
        "observacoes": "",
        "vaga": "ALTA PRESSAO - GPS - 01 - 24 HS",
        "equipamento": "DSY6F81",
        "atraso": {
          "houve": "No",
          "horarioDirecionamento": "",
          "motivo": "",
          "justificativa": ""
        },
        "trocas": [
          {
            "motivo": "Defeitos Em Geral",
            "placaNova": "EAM 3262",
            "defeito": "DSY6F81 estourou ouring do cabeote.\nFoi passado pra manuteno",
            "dataHoraInicio": "2025-08-31T10:00",
            "dataHoraFim": "2025-08-31T10:10"
          }
        ],
        "implementos": {
          "implemento_Pistola": "OK",
          "implemento_Pistola_C_L_": "N/A",
          "implemento_Mang__Torpedo": "OK",
          "implemento_Pedal": "N/A",
          "implemento_Varetas": "N/A",
          "implemento_Rabicho": "N/A",
          "implemento_Lances_Mangueira": "4",
          "implemento_Lances_Varetas": "N/A",
          "justificativa_implementos": "",
          "caixa_bloqueio": "Sim",
          "cadeados": "4",
          "plaquetas": "3"
        }
      },
      {
        "tipo": "Alta Pressao",
        "numero": "",
        "motorista": "Adelson Alves",
        "operadores": "Paulo Cesar e David Silveira Vasconcelos",
        "area": "Sinterizao",
        "atividade": "Limpeza de estruturas",
        "tipoAtividade": "Rotineira",
        "statusAtividade": "Concludo",
        "pendencia": "",
        "observacoes": "",
        "vaga": "ALTA PRESSAO - GPS - 08 - 24 HS",
        "equipamento": "EAM3253",
        "atraso": {
          "houve": "No",
          "horarioDirecionamento": "",
          "motivo": "",
          "justificativa": ""
        },
        "trocas": [],
        "implementos": {
          "implemento_Pistola": "OK",
          "implemento_Pistola_C_L_": "N/A",
          "implemento_Mang__Torpedo": "OK",
          "implemento_Pedal": "OK",
          "implemento_Varetas": "N/A",
          "implemento_Rabicho": "N/A",
          "implemento_Lances_Mangueira": "4",
          "implemento_Lances_Varetas": "N/A",
          "justificativa_implementos": "",
          "caixa_bloqueio": "Sim",
          "cadeados": "6",
          "plaquetas": "7"
        }
      },
      {
        "tipo": "Alta Pressao",
        "numero": "",
        "motorista": "N/A",
        "operadores": "Claudinei de Souza e Joao Paulo de Castro Vasconcelos",
        "area": "Coqueria 02",
        "atividade": "Limpeza de portas e pisos",
        "tipoAtividade": "Rotineira",
        "statusAtividade": "Concludo",
        "pendencia": "",
        "observacoes": "",
        "vaga": "Moto bomba 01",
        "equipamento": "Moto bomba 01",
        "atraso": {
          "houve": "No",
          "horarioDirecionamento": "",
          "motivo": "",
          "justificativa": ""
        },
        "trocas": [],
        "implementos": {
          "implemento_Pistola": "OK",
          "implemento_Pistola_C_L_": "N/A",
          "implemento_Mang__Torpedo": "N/A",
          "implemento_Pedal": "N/A",
          "implemento_Varetas": "N/A",
          "implemento_Rabicho": "N/A",
          "implemento_Lances_Mangueira": "11",
          "implemento_Lances_Varetas": "N/A",
          "justificativa_implementos": "",
          "caixa_bloqueio": "No",
          "cadeados": "N/A",
          "plaquetas": "N/A"
        }
      },
      {
        "tipo": "Auto Vacuo / Hiper Vacuo",
        "numero": "",
        "motorista": "Maxwuel Afonso",
        "operadores": "Renato silva",
        "area": "rea interna usiminas",
        "atividade": "Suco de condensado de BFG",
        "tipoAtividade": "Rotineira",
        "statusAtividade": "Concludo",
        "pendencia": "",
        "observacoes": "",
        "vaga": "AUTO VACUO - GPS - 02 - 16 HS",
        "equipamento": "ALY5322",
        "atraso": {
          "houve": "No",
          "horarioDirecionamento": "",
          "motivo": "",
          "justificativa": ""
        },
        "trocas": [],
        "implementos": {
          "implemento_Mangotes": "N/A",
          "implemento_Reducoes": "N/A",
          "implemento_Mangotes_3_": "N/A",
          "implemento_Mangotes_4_": "N/A",
          "implemento_Mangotes_6_": "N/A",
          "justificativa_implementos": "",
          "caixa_bloqueio": "No",
          "cadeados": "N/A",
          "plaquetas": "N/A"
        }
      },
      {
        "tipo": "Auto Vacuo / Hiper Vacuo",
        "numero": "",
        "motorista": "Walace das Graas",
        "operadores": "Romulo de Souza",
        "area": "ENA e sinterizao",
        "atividade": "Sucao de lama na ena e agua no silo 44 na sinter",
        "tipoAtividade": "Rotineira",
        "statusAtividade": "Concludo",
        "pendencia": "",
        "observacoes": "",
        "vaga": "AUTO VACUO - GPS - 08 - 24 HS",
        "equipamento": "EAM3251",
        "atraso": {
          "houve": "No",
          "horarioDirecionamento": "",
          "motivo": "",
          "justificativa": ""
        },
        "trocas": [],
        "implementos": {
          "implemento_Mangotes": "OK",
          "implemento_Reducoes": "N/A",
          "implemento_Mangotes_3_": "20 metros",
          "implemento_Mangotes_4_": "20 metros",
          "implemento_Mangotes_6_": "N/A",
          "justificativa_implementos": "",
          "caixa_bloqueio": "No",
          "cadeados": "N/A",
          "plaquetas": "N/A"
        }
      }
    ],
    "observacoesGerais": "",
    "estatisticas": {
      "totalEquipes": 5,
      "equipesAltaPressao": 3,
      "equipesVacuo": 0,
      "equipesExtras": 0,
      "atividadesConcluidas": 5,
      "totalTrocas": 1,
      "equipesComAtraso": 0
    },
    "criadoPor": "GrupoGPS",
    "criadoEm": "2025-08-31T21:14:00.591Z"
  },
  {
    "id": "REL1756287704344",
    "dadosTurno": {
      "data": "2025-08-26",
      "horario": "19:00 - 07:00",
      "letra": "A",
      "supervisor": "Ozias"
    },
    "equipes": [
      {
        "tipo": "Alta Pressao",
        "numero": "",
        "motorista": "Gerlanio Silves",
        "operadores": "Paulo Bras e Fabrcio Fabiano",
        "area": "Alto forno e Sinterizaao",
        "atividade": "Limpeza de peneira ,estruturas.",
        "tipoAtividade": "Rotineira",
        "statusAtividade": "Concludo",
        "pendencia": "",
        "observacoes": "",
        "vaga": "ALTA PRESSAO - GPS - 01 - 24 HS",
        "equipamento": "EAM3262",
        "atraso": {
          "houve": "No",
          "horarioDirecionamento": "",
          "motivo": "",
          "justificativa": ""
        },
        "trocas": [
          {
            "motivo": "Defeitos Em Geral",
            "placaNova": "EAM 3253",
            "defeito": "equipamento estourou mangueira sada do cabeote",
            "dataHoraInicio": "2025-08-27T01:30",
            "dataHoraFim": "2025-08-27T01:45"
          }
        ],
        "implementos": {
          "implemento_Pistola": "OK",
          "implemento_Pistola_C_L_": "N/A",
          "implemento_Mang__Torpedo": "N/A",
          "implemento_Pedal": "N/A",
          "implemento_Varetas": "N/A",
          "implemento_Rabicho": "N/A",
          "implemento_Lances_Mangueira": "4",
          "implemento_Lances_Varetas": "N/A",
          "justificativa_implementos": "",
          "caixa_bloqueio": "No",
          "cadeados": "N/A",
          "plaquetas": "N/A"
        }
      },
      {
        "tipo": "Alta Pressao",
        "numero": "",
        "motorista": "Adelson Alves",
        "operadores": "Paulo Cesar e David Silveira Vasconcelos",
        "area": "Sinterizao e ptio de carvo",
        "atividade": "limpeza de estrutura na sinter e poo da C 08 no ptio de carvo",
        "tipoAtividade": "Rotineira",
        "statusAtividade": "Concludo",
        "pendencia": "",
        "observacoes": "",
        "vaga": "ALTA PRESSAO - GPS - 08 - 24 HS",
        "equipamento": "EGC2985",
        "atraso": {
          "houve": "No",
          "horarioDirecionamento": "",
          "motivo": "",
          "justificativa": ""
        },
        "trocas": [
          {
            "motivo": "Solicitao Do Cliente",
            "placaNova": "ANF 2676",
            "defeito": "troca de alta presso por vcuo",
            "dataHoraInicio": "2025-08-27T01:15",
            "dataHoraFim": "2025-08-27T01:20"
          }
        ],
        "implementos": {
          "implemento_Pistola": "OK",
          "implemento_Pistola_C_L_": "N/A",
          "implemento_Mang__Torpedo": "OK",
          "implemento_Pedal": "N/A",
          "implemento_Varetas": "N/A",
          "implemento_Rabicho": "N/A",
          "implemento_Lances_Mangueira": "4",
          "implemento_Lances_Varetas": "N/A",
          "justificativa_implementos": "",
          "caixa_bloqueio": "Sim",
          "cadeados": "5",
          "plaquetas": "5"
        }
      },
      {
        "tipo": "Alta Pressao",
        "numero": "",
        "motorista": "N/A",
        "operadores": "Cristiano de Abreu e Claudinei de Souza",
        "area": "Coqueria 02",
        "atividade": "Limpeza de portas e patio",
        "tipoAtividade": "Rotineira",
        "statusAtividade": "Concludo",
        "pendencia": "",
        "observacoes": "",
        "vaga": "Moto bomba 01",
        "equipamento": "Moto bomba 01",
        "atraso": {
          "houve": "No",
          "horarioDirecionamento": "",
          "motivo": "",
          "justificativa": ""
        },
        "trocas": [],
        "implementos": {
          "implemento_Pistola": "OK",
          "implemento_Pistola_C_L_": "N/A",
          "implemento_Mang__Torpedo": "N/A",
          "implemento_Pedal": "N/A",
          "implemento_Varetas": "N/A",
          "implemento_Rabicho": "N/A",
          "implemento_Lances_Mangueira": "11",
          "implemento_Lances_Varetas": "N/A",
          "justificativa_implementos": "",
          "caixa_bloqueio": "No",
          "cadeados": "N/A",
          "plaquetas": "N/A"
        }
      },
      {
        "tipo": "Auto Vacuo / Hiper Vacuo",
        "numero": "",
        "motorista": "Walace das Graas",
        "operadores": "Romulo de Souza",
        "area": "Ptio 02 da hasco",
        "atividade": "suco de agua no patio",
        "tipoAtividade": "Rotineira",
        "statusAtividade": "Concludo",
        "pendencia": "",
        "observacoes": "",
        "vaga": "ALTA PRESSAO - GPS - 08 - 24 HS",
        "equipamento": "EGC2993",
        "atraso": {
          "houve": "No",
          "horarioDirecionamento": "",
          "motivo": "",
          "justificativa": ""
        },
        "trocas": [],
        "implementos": {
          "implemento_Mangotes": "OK",
          "implemento_Reducoes": "OK",
          "implemento_Mangotes_3_": "20 metros",
          "implemento_Mangotes_4_": "20 metros",
          "implemento_Mangotes_6_": "N/A",
          "justificativa_implementos": "",
          "caixa_bloqueio": "No",
          "cadeados": "N/A",
          "plaquetas": "N/A"
        }
      },
      {
        "tipo": "Auto Vacuo / Hiper Vacuo",
        "numero": "",
        "motorista": "Diego Claudio",
        "operadores": "Gilson do Carmo",
        "area": "Area interna usiminas",
        "atividade": "Suco de condensado de COG",
        "tipoAtividade": "Rotineira",
        "statusAtividade": "Concludo",
        "pendencia": "",
        "observacoes": "",
        "vaga": "AUTO VACUO - GPS - 01 - 16 HS",
        "equipamento": "EAM3257",
        "atraso": {
          "houve": "No",
          "horarioDirecionamento": "",
          "motivo": "",
          "justificativa": ""
        },
        "trocas": [],
        "implementos": {
          "implemento_Mangotes": "OK",
          "implemento_Reducoes": "N/A",
          "implemento_Mangotes_3_": "10 metros",
          "implemento_Mangotes_4_": "N/A",
          "implemento_Mangotes_6_": "N/A",
          "justificativa_implementos": "",
          "caixa_bloqueio": "No",
          "cadeados": "N/A",
          "plaquetas": "N/A"
        }
      }
    ],
    "observacoesGerais": "Troca de alta presso 08 por vcuo as 01:15, vcuo ANF 2676\nAlta presso 01 ,EAM 3262 estourou mangueira do cabeote foi trocado as 01:45 por AP EAM 3253",
    "estatisticas": {
      "totalEquipes": 5,
      "equipesAltaPressao": 3,
      "equipesVacuo": 0,
      "equipesExtras": 0,
      "atividadesConcluidas": 5,
      "totalTrocas": 2,
      "equipesComAtraso": 0
    },
    "criadoPor": "GrupoGPS",
    "criadoEm": "2025-08-27T09:41:44.345Z"
  },
  {
    "id": "REL1756200980627",
    "dadosTurno": {
      "data": "2025-08-25",
      "horario": "19:00 - 07:00",
      "letra": "A",
      "supervisor": "Ozias"
    },
    "equipes": [
      {
        "tipo": "Alta Pressao",
        "numero": "",
        "motorista": "Walisson Lucas",
        "operadores": "Bruno e Vinicios",
        "area": "Sinterizaao",
        "atividade": "Limpeza de estrutura na MS 02",
        "tipoAtividade": "Rotineira",
        "statusAtividade": "Concludo",
        "pendencia": "",
        "observacoes": "",
        "vaga": "ALTA PRESSAO - GPS - 01 - 24 HS",
        "equipamento": "EGC2989",
        "atraso": {
          "houve": "No",
          "horarioDirecionamento": "",
          "motivo": "",
          "justificativa": ""
        },
        "trocas": [],
        "implementos": {
          "implemento_Pistola": "OK",
          "implemento_Pistola_C_L_": "N/A",
          "implemento_Mang__Torpedo": "N/A",
          "implemento_Pedal": "N/A",
          "implemento_Varetas": "N/A",
          "implemento_Rabicho": "N/A",
          "implemento_Lances_Mangueira": "4",
          "implemento_Lances_Varetas": "N/A",
          "justificativa_implementos": "",
          "caixa_bloqueio": "Sim",
          "cadeados": "4",
          "plaquetas": "4"
        }
      },
      {
        "tipo": "Alta Pressao",
        "numero": "",
        "motorista": "Adelson Alves",
        "operadores": "Paulo Cesar e David Silveira Vasconcelos",
        "area": "Sinterizao e TPG 01",
        "atividade": "LImpeza de pisos e canaletas no TPG e ct C  A102  na sinterizao",
        "tipoAtividade": "Rotineira",
        "statusAtividade": "Concludo",
        "pendencia": "",
        "observacoes": "",
        "vaga": "ALTA PRESSAO - GPS - 08 - 24 HS",
        "equipamento": "EGC2985",
        "atraso": {
          "houve": "No",
          "horarioDirecionamento": "",
          "motivo": "",
          "justificativa": ""
        },
        "trocas": [],
        "implementos": {
          "implemento_Pistola": "OK",
          "implemento_Pistola_C_L_": "N/A",
          "implemento_Mang__Torpedo": "OK",
          "implemento_Pedal": "OK",
          "implemento_Varetas": "N/A",
          "implemento_Rabicho": "N/A",
          "implemento_Lances_Mangueira": "4",
          "implemento_Lances_Varetas": "N/A",
          "justificativa_implementos": "",
          "caixa_bloqueio": "Sim",
          "cadeados": "5",
          "plaquetas": "6"
        }
      },
      {
        "tipo": "Alta Pressao",
        "numero": "",
        "motorista": "N/A",
        "operadores": "Cristiano de Abreu e Claudinei de Souza",
        "area": "Coqueria 02",
        "atividade": "Limpeza de ptio e pisos",
        "tipoAtividade": "Rotineira",
        "statusAtividade": "Concludo",
        "pendencia": "",
        "observacoes": "",
        "vaga": "Moto bomba 01",
        "equipamento": "Moto bomba 01",
        "atraso": {
          "houve": "No",
          "horarioDirecionamento": "",
          "motivo": "",
          "justificativa": ""
        },
        "trocas": [],
        "implementos": {
          "implemento_Pistola": "OK",
          "implemento_Pistola_C_L_": "N/A",
          "implemento_Mang__Torpedo": "N/A",
          "implemento_Pedal": "N/A",
          "implemento_Varetas": "N/A",
          "implemento_Rabicho": "N/A",
          "implemento_Lances_Mangueira": "11",
          "implemento_Lances_Varetas": "N/A",
          "justificativa_implementos": "",
          "caixa_bloqueio": "No",
          "cadeados": "N/A",
          "plaquetas": "N/A"
        }
      },
      {
        "tipo": "Auto Vacuo / Hiper Vacuo",
        "numero": "",
        "motorista": "Walace das Graas",
        "operadores": "Rmulo de Souza",
        "area": "Poo redondo e carboquimico",
        "atividade": "transporte de gua poo redondo para etol e suco de resduo de alcatro",
        "tipoAtividade": "Rotineira",
        "statusAtividade": "Concludo",
        "pendencia": "",
        "observacoes": "",
        "vaga": "AUTO VACUO - GPS - 08 - 24 HS",
        "equipamento": "EGC2983",
        "atraso": {
          "houve": "No",
          "horarioDirecionamento": "",
          "motivo": "",
          "justificativa": ""
        },
        "trocas": [],
        "implementos": {
          "implemento_Mangotes": "OK",
          "implemento_Reducoes": "OK",
          "implemento_Mangotes_3_": "20 metros",
          "implemento_Mangotes_4_": "20 metros",
          "implemento_Mangotes_6_": "N/A",
          "justificativa_implementos": "",
          "caixa_bloqueio": "No",
          "cadeados": "N/A",
          "plaquetas": "N/A"
        }
      },
      {
        "tipo": "Auto Vacuo / Hiper Vacuo",
        "numero": "",
        "motorista": "Diego Claudio",
        "operadores": "Gilson do Carmo",
        "area": "rea interna da Usiminas",
        "atividade": "suco de condensado de COG",
        "tipoAtividade": "Rotineira",
        "statusAtividade": "Concludo",
        "pendencia": "",
        "observacoes": "",
        "vaga": "AUTO VACUO - GPS - 01 - 16 HS",
        "equipamento": "EAM3257",
        "atraso": {
          "houve": "No",
          "horarioDirecionamento": "",
          "motivo": "",
          "justificativa": ""
        },
        "trocas": [],
        "implementos": {
          "implemento_Mangotes": "OK",
          "implemento_Reducoes": "N/A",
          "implemento_Mangotes_3_": "10 metros",
          "implemento_Mangotes_4_": "N/A",
          "implemento_Mangotes_6_": "N/A",
          "justificativa_implementos": "",
          "caixa_bloqueio": "No",
          "cadeados": "N/A",
          "plaquetas": "N/A"
        }
      }
    ],
    "observacoesGerais": "",
    "estatisticas": {
      "totalEquipes": 5,
      "equipesAltaPressao": 3,
      "equipesVacuo": 0,
      "equipesExtras": 0,
      "atividadesConcluidas": 5,
      "totalTrocas": 0,
      "equipesComAtraso": 0
    },
    "criadoPor": "GrupoGPS",
    "criadoEm": "2025-08-26T09:36:20.627Z"
  },
  {
    "id": "REL1756071357197",
    "dadosTurno": {
      "data": "2025-08-24",
      "horario": "07:00 - 19:00",
      "letra": "A",
      "supervisor": "Ozias"
    },
    "equipes": [
      {
        "tipo": "Alta Pressao",
        "numero": "",
        "motorista": "Gerlanio Silves",
        "operadores": "Paulo Brs e Fabricio Fabiano",
        "area": "Alto forno",
        "atividade": "Limpeza de peneira e poo de correia  CT 05 com vcuo",
        "tipoAtividade": "Rotineira",
        "statusAtividade": "Concludo",
        "pendencia": "",
        "observacoes": "",
        "vaga": "ALTA PRESSAO - GPS - 01 - 24 HS",
        "equipamento": "EGC2978",
        "atraso": {
          "houve": "No",
          "horarioDirecionamento": "",
          "motivo": "",
          "justificativa": ""
        },
        "trocas": [
          {
            "motivo": "Solicitao Do Cliente",
            "placaNova": "CUB 0763",
            "defeito": "realizado a troca do alta presso por vcuo a pedido do cliente",
            "dataHoraInicio": "2025-08-24T10:40",
            "dataHoraFim": "2025-08-24T13:20"
          }
        ],
        "implementos": {
          "implemento_Pistola": "OK",
          "implemento_Pistola_C_L_": "N/A",
          "implemento_Mang__Torpedo": "N/A",
          "implemento_Pedal": "N/A",
          "implemento_Varetas": "N/A",
          "implemento_Rabicho": "N/A",
          "implemento_Lances_Mangueira": "4",
          "implemento_Lances_Varetas": "N/A",
          "justificativa_implementos": "",
          "caixa_bloqueio": "Sim",
          "cadeados": "4",
          "plaquetas": "4"
        }
      },
      {
        "tipo": "Alta Pressao",
        "numero": "",
        "motorista": "Adelson Alves",
        "operadores": "Paulo Cesar e David Silveira Vasconcelos",
        "area": "CRAL 03",
        "atividade": "Limpeza de caixas e canaletas",
        "tipoAtividade": "Rotineira",
        "statusAtividade": "Concludo",
        "pendencia": "",
        "observacoes": "",
        "vaga": "ALTA PRESSAO - GPS - 08 - 24 HS",
        "equipamento": "EGC2985",
        "atraso": {
          "houve": "No",
          "horarioDirecionamento": "",
          "motivo": "",
          "justificativa": ""
        },
        "trocas": [
          {
            "motivo": "Solicitao Do Cliente",
            "placaNova": "CUB 0763",
            "defeito": "realizado a troca do alta presso por vcuo a pedido do cliente",
            "dataHoraInicio": "2025-08-24T10:40",
            "dataHoraFim": "2025-08-24T13:20"
          }
        ],
        "implementos": {
          "implemento_Pistola": "OK",
          "implemento_Pistola_C_L_": "N/A",
          "implemento_Mang__Torpedo": "OK",
          "implemento_Pedal": "OK",
          "implemento_Varetas": "N/A",
          "implemento_Rabicho": "N/A",
          "implemento_Lances_Mangueira": "4",
          "implemento_Lances_Varetas": "N/A",
          "justificativa_implementos": "",
          "caixa_bloqueio": "Sim",
          "cadeados": "6",
          "plaquetas": "6"
        }
      },
      {
        "tipo": "Alta Pressao",
        "numero": "",
        "motorista": "N/A",
        "operadores": "Cadmiel e Claudinei de Souza",
        "area": "Coqueria 02",
        "atividade": "Limpeza de portas e pisos",
        "tipoAtividade": "Rotineira",
        "statusAtividade": "Concludo",
        "pendencia": "",
        "observacoes": "",
        "vaga": "moto bomba 01",
        "equipamento": "moto bomba 01",
        "atraso": {
          "houve": "No",
          "horarioDirecionamento": "",
          "motivo": "",
          "justificativa": ""
        },
        "trocas": [],
        "implementos": {
          "implemento_Pistola": "OK",
          "implemento_Pistola_C_L_": "N/A",
          "implemento_Mang__Torpedo": "N/A",
          "implemento_Pedal": "N/A",
          "implemento_Varetas": "N/A",
          "implemento_Rabicho": "N/A",
          "implemento_Lances_Mangueira": "11",
          "implemento_Lances_Varetas": "N/A",
          "justificativa_implementos": "",
          "caixa_bloqueio": "No",
          "cadeados": "N/A",
          "plaquetas": "N/A"
        }
      },
      {
        "tipo": "Auto Vacuo / Hiper Vacuo",
        "numero": "",
        "motorista": "Walace das Graas",
        "operadores": "Romulo de Souza",
        "area": "CRAL 03",
        "atividade": "Suco de lama de canaletas caixa de decantao",
        "tipoAtividade": "Rotineira",
        "statusAtividade": "Concludo",
        "pendencia": "",
        "observacoes": "",
        "vaga": "AUTO VACUO - GPS - 08 - 24 HS",
        "equipamento": "EGC2993",
        "atraso": {
          "houve": "No",
          "horarioDirecionamento": "",
          "motivo": "",
          "justificativa": ""
        },
        "trocas": [],
        "implementos": {
          "implemento_Mangotes": "OK",
          "implemento_Reducoes": "N/A",
          "implemento_Mangotes_3_": "20 metros",
          "implemento_Mangotes_4_": "20 metros",
          "implemento_Mangotes_6_": "N/A",
          "justificativa_implementos": "",
          "caixa_bloqueio": "No",
          "cadeados": "N/A",
          "plaquetas": "N/A"
        }
      },
      {
        "tipo": "Auto Vacuo / Hiper Vacuo",
        "numero": "",
        "motorista": "Maxwel Afonso",
        "operadores": "Renato Souza",
        "area": "rea interna da usiminas",
        "atividade": "Sucao de condensado de BFG",
        "tipoAtividade": "Rotineira",
        "statusAtividade": "Concludo",
        "pendencia": "",
        "observacoes": "",
        "vaga": "AUTO VACUO - GPS - 02 - 16 HS",
        "equipamento": "ALY5322",
        "atraso": {
          "houve": "No",
          "horarioDirecionamento": "",
          "motivo": "",
          "justificativa": ""
        },
        "trocas": [],
        "implementos": {
          "implemento_Mangotes": "OK",
          "implemento_Reducoes": "N/A",
          "implemento_Mangotes_3_": "10 metros",
          "implemento_Mangotes_4_": "N/A",
          "implemento_Mangotes_6_": "N/A",
          "justificativa_implementos": "",
          "caixa_bloqueio": "No",
          "cadeados": "N/A",
          "plaquetas": "N/A"
        }
      }
    ],
    "observacoesGerais": "",
    "estatisticas": {
      "totalEquipes": 5,
      "equipesAltaPressao": 3,
      "equipesVacuo": 0,
      "equipesExtras": 0,
      "atividadesConcluidas": 5,
      "totalTrocas": 2,
      "equipesComAtraso": 0
    },
    "criadoPor": "GrupoGPS",
    "criadoEm": "2025-08-24T21:35:57.197Z"
  },
  {
    "id": "REL1755982676454",
    "dadosTurno": {
      "data": "2025-08-23",
      "horario": "07:00 - 19:00",
      "letra": "A",
      "supervisor": "Ozias"
    },
    "equipes": [
      {
        "tipo": "Alta Pressao",
        "numero": "",
        "motorista": "Gerlanio Silves",
        "operadores": "Paulo Brs e Fabricio Fabiano",
        "area": "Sinterizao",
        "atividade": "Limpeza de estruturas",
        "tipoAtividade": "Rotineira",
        "statusAtividade": "Concludo",
        "pendencia": "",
        "observacoes": "",
        "vaga": "ALTA PRESSAO - GPS - 01 - 24 HS",
        "equipamento": "EAM3253",
        "atraso": {
          "houve": "No",
          "horarioDirecionamento": "",
          "motivo": "",
          "justificativa": ""
        },
        "trocas": [],
        "implementos": {
          "implemento_Pistola": "OK",
          "implemento_Pistola_C_L_": "N/A",
          "implemento_Mang__Torpedo": "N/A",
          "implemento_Pedal": "N/A",
          "implemento_Varetas": "N/A",
          "implemento_Rabicho": "N/A",
          "implemento_Lances_Mangueira": "4",
          "implemento_Lances_Varetas": "N/A",
          "justificativa_implementos": "",
          "caixa_bloqueio": "Sim",
          "cadeados": "4",
          "plaquetas": "4"
        }
      },
      {
        "tipo": "Alta Pressao",
        "numero": "",
        "motorista": "Adelson Alves",
        "operadores": "Paulo Cesar",
        "area": "crade e coqueria 02",
        "atividade": "suco de lama no crade e limpeza de rotor na coqueria",
        "tipoAtividade": "Rotineira",
        "statusAtividade": "Concludo",
        "pendencia": "",
        "observacoes": "",
        "vaga": "ALTA PRESSAO - GPS - 08 - 24 HS",
        "equipamento": "PUB2F80",
        "atraso": {
          "houve": "No",
          "horarioDirecionamento": "",
          "motivo": "",
          "justificativa": ""
        },
        "trocas": [
          {
            "motivo": "Solicitao Do Cliente",
            "placaNova": "CUB 0763",
            "defeito": "troca de alta pressa por vcuo",
            "dataHoraInicio": "2025-08-23T08:40",
            "dataHoraFim": "2025-08-23T08:52"
          }
        ],
        "implementos": {
          "implemento_Pistola": "OK",
          "implemento_Pistola_C_L_": "N/A",
          "implemento_Mang__Torpedo": "OK",
          "implemento_Pedal": "OK",
          "implemento_Varetas": "N/A",
          "implemento_Rabicho": "N/A",
          "implemento_Lances_Mangueira": "4",
          "implemento_Lances_Varetas": "N/A",
          "justificativa_implementos": "",
          "caixa_bloqueio": "Sim",
          "cadeados": "6",
          "plaquetas": "6"
        }
      },
      {
        "tipo": "Alta Pressao",
        "numero": "",
        "motorista": "N/A",
        "operadores": "Claudinei de Sousa e David Silveira Vasconcelos",
        "area": "Coqueria 02",
        "atividade": "Limpeza de portas",
        "tipoAtividade": "Rotineira",
        "statusAtividade": "Concludo",
        "pendencia": "",
        "observacoes": "",
        "vaga": "moto bomba 01",
        "equipamento": "moto bomba 01",
        "atraso": {
          "houve": "No",
          "horarioDirecionamento": "",
          "motivo": "",
          "justificativa": ""
        },
        "trocas": [],
        "implementos": {
          "implemento_Pistola": "OK",
          "implemento_Pistola_C_L_": "N/A",
          "implemento_Mang__Torpedo": "N/A",
          "implemento_Pedal": "N/A",
          "implemento_Varetas": "N/A",
          "implemento_Rabicho": "N/A",
          "implemento_Lances_Mangueira": "10",
          "implemento_Lances_Varetas": "N/A",
          "justificativa_implementos": "",
          "caixa_bloqueio": "No",
          "cadeados": "N/A",
          "plaquetas": "N/A"
        }
      },
      {
        "tipo": "Auto Vacuo / Hiper Vacuo",
        "numero": "",
        "motorista": "Maxwel Afonso",
        "operadores": "Renato Silva Ramos",
        "area": "rea interna usiminas",
        "atividade": "Suco de condensado de BFG",
        "tipoAtividade": "Rotineira",
        "statusAtividade": "Concludo",
        "pendencia": "",
        "observacoes": "",
        "vaga": "AUTO VACUO - GPS - 02 - 16 HS",
        "equipamento": "ALY5322",
        "atraso": {
          "houve": "No",
          "horarioDirecionamento": "",
          "motivo": "",
          "justificativa": ""
        },
        "trocas": [],
        "implementos": {
          "implemento_Mangotes": "OK",
          "implemento_Reducoes": "N/A",
          "implemento_Mangotes_3_": "10 metros",
          "implemento_Mangotes_4_": "N/A",
          "implemento_Mangotes_6_": "N/A",
          "justificativa_implementos": "",
          "caixa_bloqueio": "No",
          "cadeados": "N/A",
          "plaquetas": "N/A"
        }
      },
      {
        "tipo": "Auto Vacuo / Hiper Vacuo",
        "numero": "",
        "motorista": "Walace das Graas",
        "operadores": "Romulo de Souza",
        "area": "OG 02 e CRADE",
        "atividade": "Suco de lama",
        "tipoAtividade": "Rotineira",
        "statusAtividade": "Concludo",
        "pendencia": "",
        "observacoes": "",
        "vaga": "AUTO VACUO - GPS - 08 - 24 HS",
        "equipamento": "EGC2993",
        "atraso": {
          "houve": "No",
          "horarioDirecionamento": "",
          "motivo": "",
          "justificativa": ""
        },
        "trocas": [],
        "implementos": {
          "implemento_Mangotes": "OK",
          "implemento_Reducoes": "N/A",
          "implemento_Mangotes_3_": "20 metros",
          "implemento_Mangotes_4_": "20 metros",
          "implemento_Mangotes_6_": "N/A",
          "justificativa_implementos": "",
          "caixa_bloqueio": "No",
          "cadeados": "N/A",
          "plaquetas": "N/A"
        }
      }
    ],
    "observacoesGerais": "",
    "estatisticas": {
      "totalEquipes": 5,
      "equipesAltaPressao": 3,
      "equipesVacuo": 0,
      "equipesExtras": 0,
      "atividadesConcluidas": 5,
      "totalTrocas": 1,
      "equipesComAtraso": 0
    },
    "criadoPor": "GrupoGPS",
    "criadoEm": "2025-08-23T20:57:56.454Z"
  }
]